{
  "server": {
    "handlers": {
      "pam": {
        "defaultGroups": ["admin"],
        "groups": "/etc/skylark/groups.json",
        "blacklist": "/etc/skylark/blacklist.json",
        "settings": "/home/%USERNAME%/.skylark/settings.json"
      },
      "shadow": {
        "defaultGroups": ["admin"],
        "groups": "/etc/skylark/groups.json",
        "blacklist": "/etc/skylark/blacklist.json",
        "settings": "/home/%USERNAME%/.skylark/settings.json"
      },
      "mysql": {
        "host": "localhost",
        "user": "osjs",
        "password": "osjs",
        "database": "osjs"
      }
    }
  }
}
